dustmaker/__init__.py
dustmaker/__main__.py
dustmaker/bitio.py
dustmaker/dfreader.py
dustmaker/dfwriter.py
dustmaker/entity.py
dustmaker/exceptions.py
dustmaker/level.py
dustmaker/prop.py
dustmaker/py.typed
dustmaker/replay.py
dustmaker/tile.py
dustmaker/transform.py
dustmaker/variable.py
dustmaker/cmd/__init__.py
dustmaker/cmd/common.py
dustmaker/cmd/main.py
dustmaker/cmd/save_convert.py
dustmaker/cmd/thumbnail.py
dustmaker/cmd/transform.py
dustmaker/cmd/variables.py
dustmaker-1.2.0.dist-info/LICENSE.txt
dustmaker-1.2.0.dist-info/METADATA
dustmaker-1.2.0.dist-info/WHEEL
dustmaker-1.2.0.dist-info/top_level.txt
dustmaker-1.2.0.dist-info/RECORD
