Metadata-Version: 2.1
Name: dustmaker
Version: 1.2.0
Summary: Dustforce level scripting framework
Home-page: http://github.com/msg555/dustmaker/
Author: Mark Gordon
Author-email: msg555@gmail.com
Classifier: Programming Language :: Python :: 3
Classifier: License :: OSI Approved :: Apache Software License
Classifier: Operating System :: OS Independent
Requires-Python: >=3.6
License-File: LICENSE.txt
Requires-Dist: dataclasses ; python_version < "3.7"
